Ophis/CmdLine.py
Ophis/CorePragmas.py
Ophis/Environment.py
Ophis/Errors.py
Ophis/Frontend.py
Ophis/IR.py
Ophis/Listing.py
Ophis/Macro.py
Ophis/Main.py
Ophis/Opcodes.py
Ophis/Passes.py
Ophis/__init__.py
ophis_asm-2.2.0.post1.dist-info/LICENSE
ophis_asm-2.2.0.post1.dist-info/METADATA
ophis_asm-2.2.0.post1.dist-info/WHEEL
ophis_asm-2.2.0.post1.dist-info/entry_points.txt
ophis_asm-2.2.0.post1.dist-info/top_level.txt
ophis_asm-2.2.0.post1.dist-info/RECORD
