Metadata-Version: 2.1
Name: ophis-asm
Version: 2.2.0.post1
Summary: A cross-assembler for the 6502 series of chips
Author-email: Michael Martin <mcmartin@gmail.com>
Classifier: Programming Language :: Python :: 3
Classifier: License :: OSI Approved :: MIT License
Classifier: Operating System :: OS Independent
Classifier: Development Status :: 5 - Production/Stable
Classifier: Environment :: Console
Classifier: Intended Audience :: Developers
Classifier: Topic :: Software Development :: Assemblers
Requires-Python: >=3.6
License-File: LICENSE
